<?xml version="1.0" encoding="utf-8"?>
<xliff xmlns="urn:oasis:names:tc:xliff:document:1.2" xmlns:xsi="http://www.w3.org/2001/XMLSchema-instance" version="1.2" xsi:schemaLocation="urn:oasis:names:tc:xliff:document:1.2 xliff-core-1.2-transitional.xsd">
  <file datatype="xml" original="SoapFaultSubCode.xml" source-language="en-US" target-language="ru-RU">
    <header>
      <tool tool-id="mdxliff" tool-name="mdxliff" tool-version="1.0-567ae5a" tool-company="Microsoft" />
      <xliffext:skl_file_name xmlns:xliffext="urn:microsoft:content:schema:xliffextensions">7c5b04be-ac4f-4958-bcde-0afae05845525ae0e15574e4b9f0ad681d9f0ba1868c71a1bb15.skl</xliffext:skl_file_name>
      <xliffext:version xmlns:xliffext="urn:microsoft:content:schema:xliffextensions">1.2</xliffext:version>
      <xliffext:ms.openlocfilehash xmlns:xliffext="urn:microsoft:content:schema:xliffextensions">5ae0e15574e4b9f0ad681d9f0ba1868c71a1bb15</xliffext:ms.openlocfilehash>
      <xliffext:ms.sourcegitcommit xmlns:xliffext="urn:microsoft:content:schema:xliffextensions">3507e865a3613c00760f25ad1045aaa11bae4dd8</xliffext:ms.sourcegitcommit>
      <xliffext:ms.lasthandoff xmlns:xliffext="urn:microsoft:content:schema:xliffextensions">04/23/2018</xliffext:ms.lasthandoff>
      <xliffext:moniker_ids xmlns:xliffext="urn:microsoft:content:schema:xliffextensions">netframework-4.5.1,netframework-4.5.2,netframework-4.5,netframework-4.6.1,netframework-4.6.2,netframework-4.6,netframework-4.7.1,netframework-4.7.2,netframework-4.7,xamarinandroid-7.1,xamarinios-10.8,xamarinmac-3.0</xliffext:moniker_ids>
    </header>
    <body>
      <group id="content" extype="content">
        <trans-unit id="101" translate="yes" xml:space="preserve" uid="T:System.Web.Services.Protocols.SoapFaultSubCode">
          <source>Represents the contents of the optional <ph id="ph1">&lt;see langword="Subcode" /&gt;</ph> element of a SOAP fault when SOAP version 1.2 is used to communicate between a client and an XML Web service.</source>
          <target state="translated">Представляет содержимое необязательного элемента <ph id="ph1">&lt;see langword="Subcode" /&gt;</ph> ошибки SOAP, когда для взаимодействия клиента и веб-службы XML используется стандарт SOAP версии 1.2.</target>       </trans-unit>
        <trans-unit id="102" translate="yes" xml:space="preserve" extradata="MT" uid="T:System.Web.Services.Protocols.SoapFaultSubCode">
          <source>A SOAP 1.2 fault contains a <ph id="ph1">`Code`</ph> element and among other things an optional <ph id="ph2">`Subcode`</ph> element.</source>
          <target state="translated">Содержит ошибку SOAP 1.2 <ph id="ph1">`Code`</ph> элемента и многое другое значение необязательно <ph id="ph2">`Subcode`</ph> элемента.</target>       </trans-unit>
        <trans-unit id="103" translate="yes" xml:space="preserve" extradata="MT" uid="T:System.Web.Services.Protocols.SoapFaultSubCode">
          <source>The <ph id="ph1">`Code`</ph> element specifies the type of error that occurred using a limited number of pre-defined error codes specified by the SOAP protocol, whereas the <ph id="ph2">`Subcode`</ph> element allows the sender of the SOAP fault to provide an application specific error code.</source>
          <target state="translated"><ph id="ph1">`Code`</ph> Элемент задает тип происшедшей ошибки, используя ограниченное число предварительно определенных кодов ошибок заданную этим протоколом SOAP, тогда как <ph id="ph2">`Subcode`</ph> элемент позволяет отправителю ошибки SOAP для предоставления определенных ошибка приложения код.</target>       </trans-unit>
        <trans-unit id="104" translate="yes" xml:space="preserve" extradata="MT" uid="T:System.Web.Services.Protocols.SoapFaultSubCode">
          <source>This class represents the contents of the <ph id="ph1">`Subcode`</ph> element.</source>
          <target state="translated">Этот класс представляет содержимое <ph id="ph1">`Subcode`</ph> элемента.</target>       </trans-unit>
        <trans-unit id="105" translate="yes" xml:space="preserve" extradata="MT" uid="T:System.Web.Services.Protocols.SoapFaultSubCode">
          <source>XML Web services return a SOAP fault by throwing a <ph id="ph1">&lt;xref:System.Web.Services.Protocols.SoapException&gt;</ph>, and .NET clients receive a SOAP fault by catching a <ph id="ph2">&lt;xref:System.Web.Services.Protocols.SoapException&gt;</ph>.</source>
          <target state="translated">Веб-службы XML возвращать ошибку SOAP, путем создания исключения <ph id="ph1">&lt;xref:System.Web.Services.Protocols.SoapException&gt;</ph>, и клиенты .NET получают ошибки SOAP путем перехвата <ph id="ph2">&lt;xref:System.Web.Services.Protocols.SoapException&gt;</ph>.</target>       </trans-unit>
        <trans-unit id="106" translate="yes" xml:space="preserve" extradata="MT" uid="T:System.Web.Services.Protocols.SoapFaultSubCode">
          <source>A <ph id="ph1">&lt;xref:System.Web.Services.Protocols.SoapException&gt;</ph> has a <ph id="ph2">&lt;xref:System.Web.Services.Protocols.SoapException.Code%2A&gt;</ph> property that represents the <ph id="ph3">`Code`</ph> element and a <ph id="ph4">&lt;xref:System.Web.Services.Protocols.SoapException.SubCode%2A&gt;</ph> property that represents the <ph id="ph5">`Subcode`</ph> element.</source>
          <target state="translated">Объект <ph id="ph1">&lt;xref:System.Web.Services.Protocols.SoapException&gt;</ph> имеет <ph id="ph2">&lt;xref:System.Web.Services.Protocols.SoapException.Code%2A&gt;</ph> свойства, представляющего <ph id="ph3">`Code`</ph> элемент и <ph id="ph4">&lt;xref:System.Web.Services.Protocols.SoapException.SubCode%2A&gt;</ph> свойства, представляющего <ph id="ph5">`Subcode`</ph> элемента.</target>       </trans-unit>
        <trans-unit id="107" translate="yes" xml:space="preserve" uid="T:System.Web.Services.Protocols.SoapFaultSubCode">
          <source>Initializes a new instance of the <ph id="ph1">&lt;see cref="T:System.Web.Services.Protocols.SoapFaultSubcode" /&gt;</ph> class.</source>
          <target state="translated">Инициализирует новый экземпляр класса <ph id="ph1">&lt;see cref="T:System.Web.Services.Protocols.SoapFaultSubcode" /&gt;</ph>.</target>       </trans-unit>
        <trans-unit id="108" translate="yes" xml:space="preserve" uid="M:System.Web.Services.Protocols.SoapFaultSubCode.#ctor(System.Xml.XmlQualifiedName)">
          <source>An <ph id="ph1">&lt;see cref="T:System.Xml.XmlQualifiedName" /&gt;</ph> specifying the application specific error code.</source>
          <target state="translated">Объект <ph id="ph1">&lt;see cref="T:System.Xml.XmlQualifiedName" /&gt;</ph>, задающий код ошибки, характерной для приложения.</target>       </trans-unit>
        <trans-unit id="109" translate="yes" xml:space="preserve" uid="M:System.Web.Services.Protocols.SoapFaultSubCode.#ctor(System.Xml.XmlQualifiedName)">
          <source>Sets the <ph id="ph1">&lt;see cref="P:System.Web.Services.Protocols.SoapFaultSubCode.Code" /&gt;</ph> property.</source>
          <target state="translated">Задает свойство <ph id="ph1">&lt;see cref="P:System.Web.Services.Protocols.SoapFaultSubCode.Code" /&gt;</ph>.</target>       </trans-unit>
        <trans-unit id="110" translate="yes" xml:space="preserve" uid="M:System.Web.Services.Protocols.SoapFaultSubCode.#ctor(System.Xml.XmlQualifiedName)">
          <source>Initializes a new instance of the <ph id="ph1">&lt;see cref="T:System.Web.Services.Protocols.SoapFaultSubCode" /&gt;</ph> class and sets the application specific error code.</source>
          <target state="translated">Инициализирует новый экземпляр класса <ph id="ph1">&lt;see cref="T:System.Web.Services.Protocols.SoapFaultSubCode" /&gt;</ph>, который задает код ошибки, характерной для приложения.</target>       </trans-unit>
        <trans-unit id="111" translate="yes" xml:space="preserve" uid="M:System.Web.Services.Protocols.SoapFaultSubCode.#ctor(System.Xml.XmlQualifiedName,System.Web.Services.Protocols.SoapFaultSubCode)">
          <source>An <ph id="ph1">&lt;see cref="T:System.Xml.XmlQualifiedName" /&gt;</ph> specifying the application specific error code.</source>
          <target state="translated">Объект <ph id="ph1">&lt;see cref="T:System.Xml.XmlQualifiedName" /&gt;</ph>, задающий код ошибки, характерной для приложения.</target>       </trans-unit>
        <trans-unit id="112" translate="yes" xml:space="preserve" uid="M:System.Web.Services.Protocols.SoapFaultSubCode.#ctor(System.Xml.XmlQualifiedName,System.Web.Services.Protocols.SoapFaultSubCode)">
          <source>Sets the <ph id="ph1">&lt;see cref="P:System.Web.Services.Protocols.SoapFaultSubCode.Code" /&gt;</ph> property.</source>
          <target state="translated">Задает свойство <ph id="ph1">&lt;see cref="P:System.Web.Services.Protocols.SoapFaultSubCode.Code" /&gt;</ph>.</target>       </trans-unit>
        <trans-unit id="113" translate="yes" xml:space="preserve" uid="M:System.Web.Services.Protocols.SoapFaultSubCode.#ctor(System.Xml.XmlQualifiedName,System.Web.Services.Protocols.SoapFaultSubCode)">
          <source>Initializes a new instance of the <ph id="ph1">&lt;see cref="T:System.Web.Services.Protocols.SoapFaultSubCode" /&gt;</ph> class setting the application specific error code and additional error information.</source>
          <target state="translated">Инициализирует новый экземпляр класса <ph id="ph1">&lt;see cref="T:System.Web.Services.Protocols.SoapFaultSubCode" /&gt;</ph>, задающий код ошибки, характерной для приложения, и дополнительные сведения об ошибке.</target>       </trans-unit>
        <trans-unit id="114" translate="yes" xml:space="preserve" uid="P:System.Web.Services.Protocols.SoapFaultSubCode.Code">
          <source>Gets the application specific error code in the form of an XML qualified name.</source>
          <target state="translated">Получает код ошибки, характерной для приложения, в виде составного XML-имени.</target>       </trans-unit>
        <trans-unit id="115" translate="yes" xml:space="preserve" extradata="MT" uid="P:System.Web.Services.Protocols.SoapFaultSubCode.Code">
          <source>An <ph id="ph1">&lt;see cref="T:System.Xml.XmlQualifiedName" /&gt;</ph> representing the application specific error code.</source>
          <target state="translated">Объект <ph id="ph1">&lt;see cref="T:System.Xml.XmlQualifiedName" /&gt;</ph>, представляющий код ошибки, характерной для приложения.</target>       </trans-unit>
        <trans-unit id="116" translate="yes" xml:space="preserve" extradata="MT" uid="P:System.Web.Services.Protocols.SoapFaultSubCode.Code">
          <source>Use a constructor to set the <ph id="ph1">&lt;xref:System.Web.Services.Protocols.SoapFaultSubCode.Code%2A&gt;</ph> property.</source>
          <target state="translated">Используйте конструктор, чтобы задать <ph id="ph1">&lt;xref:System.Web.Services.Protocols.SoapFaultSubCode.Code%2A&gt;</ph> свойства.</target>       </trans-unit>
        <trans-unit id="117" translate="yes" xml:space="preserve" extradata="MT" uid="P:System.Web.Services.Protocols.SoapFaultSubCode.Code">
          <source>The value of the <ph id="ph1">&lt;xref:System.Web.Services.Protocols.SoapFaultSubCode.Code%2A&gt;</ph> property can be any user defined XML qualified name, including the codes represented by the <ph id="ph2">&lt;xref:System.Web.Services.Protocols.Soap12FaultCodes.RpcProcedureNotPresentFaultCode?displayProperty=nameWithType&gt;</ph>, <ph id="ph3">&lt;xref:System.Web.Services.Protocols.Soap12FaultCodes.RpcBadArgumentsFaultCode?displayProperty=nameWithType&gt;</ph>, <ph id="ph4">&lt;xref:System.Web.Services.Protocols.Soap12FaultCodes.EncodingMissingIdFaultCode?displayProperty=nameWithType&gt;</ph>, and <ph id="ph5">&lt;xref:System.Web.Services.Protocols.Soap12FaultCodes.EncodingUntypedValueFaultCode?displayProperty=nameWithType&gt;</ph> fields.</source>
          <target state="translated">Значение <ph id="ph1">&lt;xref:System.Web.Services.Protocols.SoapFaultSubCode.Code%2A&gt;</ph> свойство может быть любой определяемой пользователем полное имя XML, включая коды, представленного <ph id="ph2">&lt;xref:System.Web.Services.Protocols.Soap12FaultCodes.RpcProcedureNotPresentFaultCode?displayProperty=nameWithType&gt;</ph>, <ph id="ph3">&lt;xref:System.Web.Services.Protocols.Soap12FaultCodes.RpcBadArgumentsFaultCode?displayProperty=nameWithType&gt;</ph>, <ph id="ph4">&lt;xref:System.Web.Services.Protocols.Soap12FaultCodes.EncodingMissingIdFaultCode?displayProperty=nameWithType&gt;</ph>, и <ph id="ph5">&lt;xref:System.Web.Services.Protocols.Soap12FaultCodes.EncodingUntypedValueFaultCode?displayProperty=nameWithType&gt;</ph> поля.</target>       </trans-unit>
        <trans-unit id="118" translate="yes" xml:space="preserve" uid="P:System.Web.Services.Protocols.SoapFaultSubCode.SubCode">
          <source>Gets additional error information contained within a child <ph id="ph1">&lt;see langword="Subcode" /&gt;</ph> element.</source>
          <target state="translated">Получает дополнительные сведения об ошибке, содержащиеся в дочернем элементе <ph id="ph1">&lt;see langword="Subcode" /&gt;</ph>.</target>       </trans-unit>
        <trans-unit id="119" translate="yes" xml:space="preserve" extradata="MT" uid="P:System.Web.Services.Protocols.SoapFaultSubCode.SubCode">
          <source>A <ph id="ph1">&lt;see cref="T:System.Web.Services.Protocols.SoapFaultSubCode" /&gt;</ph> containing additional error information.</source>
          <target state="translated">Объект <ph id="ph1">&lt;see cref="T:System.Web.Services.Protocols.SoapFaultSubCode" /&gt;</ph>, содержащий дополнительные сведения об ошибке.</target>       </trans-unit>
        <trans-unit id="120" translate="yes" xml:space="preserve" extradata="MT" uid="P:System.Web.Services.Protocols.SoapFaultSubCode.SubCode">
          <source>Use a constructor to set the <ph id="ph1">&lt;xref:System.Web.Services.Protocols.SoapFaultSubCode.SubCode%2A&gt;</ph> property.</source>
          <target state="translated">Используйте конструктор, чтобы задать <ph id="ph1">&lt;xref:System.Web.Services.Protocols.SoapFaultSubCode.SubCode%2A&gt;</ph> свойства.</target>       </trans-unit>
        <trans-unit id="121" translate="yes" xml:space="preserve" extradata="MT" uid="P:System.Web.Services.Protocols.SoapFaultSubCode.SubCode">
          <source>The <ph id="ph1">&lt;xref:System.Web.Services.Protocols.SoapFaultSubCode.SubCode%2A&gt;</ph> property allows an XML Web service to provide nested error information.</source>
          <target state="translated"><ph id="ph1">&lt;xref:System.Web.Services.Protocols.SoapFaultSubCode.SubCode%2A&gt;</ph> Свойство позволяет веб-служб XML для предоставления сведений о вложенных ошибки.</target>       </trans-unit>
        <trans-unit id="122" translate="yes" xml:space="preserve" extradata="MT" uid="P:System.Web.Services.Protocols.SoapFaultSubCode.SubCode">
          <source>This is useful for providing an error code specific to the XML Web service while passing along error information returned from components the XML Web service called.</source>
          <target state="translated">Это полезно для предоставления кода ошибки, относящиеся к веб-службу XML, при передаче сведений об ошибке, возвращенные компонентов, называемых веб-службу XML.</target>       </trans-unit>
      </group>
    </body>
  </file>
</xliff>