<?xml version="1.0" encoding="utf-8"?>
<xliff xmlns="urn:oasis:names:tc:xliff:document:1.2" xmlns:xsi="http://www.w3.org/2001/XMLSchema-instance" version="1.2" xsi:schemaLocation="urn:oasis:names:tc:xliff:document:1.2 xliff-core-1.2-transitional.xsd">
  <file datatype="xml" original="BufferedWebEventProvider.xml" source-language="en-US" target-language="ru-RU">
    <header>
      <tool tool-id="mdxliff" tool-name="mdxliff" tool-version="1.0-15c36f0" tool-company="Microsoft" />
      <xliffext:skl_file_name xmlns:xliffext="urn:microsoft:content:schema:xliffextensions">02cd5861-7ce2-4a82-b358-31f8435a0ac5460ed26394375203f2e5c82be1fd75001ffeff70.skl</xliffext:skl_file_name>
      <xliffext:version xmlns:xliffext="urn:microsoft:content:schema:xliffextensions">1.2</xliffext:version>
      <xliffext:ms.openlocfilehash xmlns:xliffext="urn:microsoft:content:schema:xliffextensions">460ed26394375203f2e5c82be1fd75001ffeff70</xliffext:ms.openlocfilehash>
      <xliffext:ms.sourcegitcommit xmlns:xliffext="urn:microsoft:content:schema:xliffextensions">d31dc2ede16f6f7bc64e90d9f897ff54c4e3869b</xliffext:ms.sourcegitcommit>
      <xliffext:ms.lasthandoff xmlns:xliffext="urn:microsoft:content:schema:xliffextensions">04/03/2018</xliffext:ms.lasthandoff>
      <xliffext:moniker_ids xmlns:xliffext="urn:microsoft:content:schema:xliffextensions">netframework-4.5.1,netframework-4.5.2,netframework-4.5,netframework-4.6.1,netframework-4.6.2,netframework-4.6,netframework-4.7.1,netframework-4.7</xliffext:moniker_ids>
    </header>
    <body>
      <group id="content" extype="content">
        <trans-unit id="101" translate="yes" xml:space="preserve" uid="T:System.Web.Management.BufferedWebEventProvider">
          <source>Provides the base functionality for creating event providers that require buffering.</source>
          <target state="translated">Обеспечивает основные функции для создания поставщиков событий, требующих буферизации.</target>       </trans-unit>
        <trans-unit id="102" translate="yes" xml:space="preserve" extradata="MT" uid="T:System.Web.Management.BufferedWebEventProvider">
          <source>ASP.NET health monitoring allows production and operations staff to manage deployed Web applications.</source>
          <target state="translated">Мониторинг состояния ASP.NET позволяет производства и операции персоналу управлять развернутыми веб-приложениями.</target>       </trans-unit>
        <trans-unit id="103" translate="yes" xml:space="preserve" extradata="MT" uid="T:System.Web.Management.BufferedWebEventProvider">
          <source>The <ph id="ph1">&lt;xref:System.Web.Management&gt;</ph> namespace contains the health-event types responsible for packaging application health-status data and the provider types responsible for processing this data.</source>
          <target state="translated"><ph id="ph1">&lt;xref:System.Web.Management&gt;</ph> Пространство имен содержит типы событий состояния, отвечающие за упаковку данных о состоянии работоспособности приложений, а также типы поставщика, ответственные за обработку этих данных.</target>       </trans-unit>
        <trans-unit id="104" translate="yes" xml:space="preserve" extradata="MT" uid="T:System.Web.Management.BufferedWebEventProvider">
          <source>It also contains supporting types that help during the management of health events.</source>
          <target state="translated">Он также содержит вспомогательные типы, которые помогут при управлении событиями состояния.</target>       </trans-unit>
        <trans-unit id="105" translate="yes" xml:space="preserve" extradata="MT" uid="T:System.Web.Management.BufferedWebEventProvider">
          <source>If you want to customize the health-event processing, you can derive from the <ph id="ph1">&lt;xref:System.Web.Management.BufferedWebEventProvider&gt;</ph> class to create your own custom buffered provider.</source>
          <target state="translated">Если вы хотите настроить обработку событий состояния, можно создать производный от <ph id="ph1">&lt;xref:System.Web.Management.BufferedWebEventProvider&gt;</ph> класса для создания собственного пользовательского поставщика с буферизацией.</target>       </trans-unit>
        <trans-unit id="106" translate="yes" xml:space="preserve" extradata="MT" uid="T:System.Web.Management.BufferedWebEventProvider">
          <source>In most cases you will be able to use the ASP.NET health-monitoring types as implemented, and you will control the health-monitoring system by specifying values in the <ph id="ph1">`healthMonitoring`</ph> configuration section.</source>
          <target state="translated">В большинстве случаев можно будет использовать типы мониторинга состояния ASP.NET как реализованные и управлять системой мониторинга состояния, указав значения в <ph id="ph1">`healthMonitoring`</ph> раздел конфигурации.</target>       </trans-unit>
        <trans-unit id="107" translate="yes" xml:space="preserve" extradata="MT" uid="T:System.Web.Management.BufferedWebEventProvider">
          <source>You can also derive from the health-monitoring types to create your own custom events and providers.</source>
          <target state="translated">Также можно наследовать от типов наблюдение за работоспособностью, чтобы создавать собственные пользовательские события и поставщиков.</target>       </trans-unit>
        <trans-unit id="108" translate="yes" xml:space="preserve" extradata="MT" uid="T:System.Web.Management.BufferedWebEventProvider">
          <source>For an example of creating a custom provider, see <bpt id="p1">[</bpt>How to: Implement the Health Monitoring Custom Provider Example<ept id="p1">](http://msdn.microsoft.com/library/bbb1c959-e6e4-42b2-be62-49b7ca5ab72c)</ept>.</source>
          <target state="translated">Пример создания пользовательского поставщика см. в разделе <bpt id="p1">[</bpt>как: реализация примера мониторинга пользовательского поставщика работоспособности<ept id="p1">](http://msdn.microsoft.com/library/bbb1c959-e6e4-42b2-be62-49b7ca5ab72c)</ept>.</target>       </trans-unit>
        <trans-unit id="109" translate="yes" xml:space="preserve" extradata="MT" uid="T:System.Web.Management.BufferedWebEventProvider">
          <source>The following code example shows how to derive from the <ph id="ph1">&lt;xref:System.Web.Management.BufferedWebEventProvider&gt;</ph> class to create a custom provider that writes the configured events to a local file for which appropriate access rights must be granted.</source>
          <target state="translated">В следующем примере кода показано, как производные от <ph id="ph1">&lt;xref:System.Web.Management.BufferedWebEventProvider&gt;</ph> класса, чтобы создать пользовательский поставщик, записывающий настроенные события в локальный файл, для которого должны быть предоставлены соответствующие права доступа.</target>       </trans-unit>
        <trans-unit id="110" translate="yes" xml:space="preserve" extradata="MT" uid="T:System.Web.Management.BufferedWebEventProvider">
          <source>The following configuration file excerpt shows a <ph id="ph1">`healthMonitoring`</ph> configuration section that enables ASP.NET to use the custom provider defined above to process all health-monitoring events.</source>
          <target state="translated">В следующем файле конфигурации фрагмент показывает <ph id="ph1">`healthMonitoring`</ph> раздел конфигурации, позволяющий ASP.NET для использования пользовательского поставщика, определенного выше, для обработки всех событий, мониторинг работоспособности.</target>       </trans-unit>
        <trans-unit id="111" translate="yes" xml:space="preserve" uid="M:System.Web.Management.BufferedWebEventProvider.#ctor">
          <source>Initializes a new instance of the <ph id="ph1">&lt;see cref="T:System.Web.Management.BufferedWebEventProvider" /&gt;</ph> class.</source>
          <target state="translated">Инициализирует новый экземпляр класса <ph id="ph1">&lt;see cref="T:System.Web.Management.BufferedWebEventProvider" /&gt;</ph>.</target>       </trans-unit>
        <trans-unit id="112" translate="yes" xml:space="preserve" extradata="MT" uid="M:System.Web.Management.BufferedWebEventProvider.#ctor">
          <source>This constructor is used internally by the ASP.NET health-monitoring system.</source>
          <target state="translated">Этот конструктор используется внутренне системой мониторинга состояния ASP.NET.</target>       </trans-unit>
        <trans-unit id="113" translate="yes" xml:space="preserve" extradata="MT" uid="M:System.Web.Management.BufferedWebEventProvider.#ctor">
          <source>You will never use it to instantiate a <ph id="ph1">&lt;xref:System.Web.Management.TraceWebEventProvider&gt;</ph> object, but you can call this constructor when implementing your own provider type that inherits from this class.</source>
          <target state="translated">Он никогда не будет использоваться для создания экземпляра <ph id="ph1">&lt;xref:System.Web.Management.TraceWebEventProvider&gt;</ph> объект, но можно вызвать этот конструктор при реализации собственного типа поставщика, который наследует от этого класса.</target>       </trans-unit>
        <trans-unit id="114" translate="yes" xml:space="preserve" extradata="MT" uid="M:System.Web.Management.BufferedWebEventProvider.#ctor">
          <source>The following code example shows how to use this constructor in a custom event provider.</source>
          <target state="translated">В следующем примере кода показано, как использовать этот конструктор в пользовательском поставщике событий.</target>       </trans-unit>
        <trans-unit id="115" translate="yes" xml:space="preserve" uid="P:System.Web.Management.BufferedWebEventProvider.BufferMode">
          <source>Gets a value indicating the buffering mode used by the provider.</source>
          <target state="translated">Получает значение, показывающее режим буферизации, используемый поставщиком.</target>       </trans-unit>
        <trans-unit id="116" translate="yes" xml:space="preserve" extradata="MT" uid="P:System.Web.Management.BufferedWebEventProvider.BufferMode">
          <source>The name of the buffering mode.</source>
          <target state="translated">Имя режима буферизации.</target>       </trans-unit>
        <trans-unit id="117" translate="yes" xml:space="preserve" extradata="MT" uid="P:System.Web.Management.BufferedWebEventProvider.BufferMode">
          <source>The <ph id="ph1">&lt;xref:System.Web.Management.BufferedWebEventProvider.BufferMode%2A&gt;</ph> property contains the value defined by the <ph id="ph2">`bufferMode`</ph> attribute in the <ph id="ph3">`providers`</ph> element of the <ph id="ph4">`healthMonitoring`</ph> section.</source>
          <target state="translated"><ph id="ph1">&lt;xref:System.Web.Management.BufferedWebEventProvider.BufferMode%2A&gt;</ph> Свойство содержит значение, определяемое <ph id="ph2">`bufferMode`</ph> атрибута в <ph id="ph3">`providers`</ph> элемент <ph id="ph4">`healthMonitoring`</ph> раздела.</target>       </trans-unit>
        <trans-unit id="118" translate="yes" xml:space="preserve" extradata="MT" uid="P:System.Web.Management.BufferedWebEventProvider.BufferMode">
          <source>The following configuration-file excerpt shows how the name of the buffer mode should be defined in the <ph id="ph1">`healthMonitoring`</ph> section.</source>
          <target state="translated">В следующем фрагменте файла конфигурации показано, как имя режима буфера должен быть определен в <ph id="ph1">`healthMonitoring`</ph> раздела.</target>       </trans-unit>
        <trans-unit id="119" translate="yes" xml:space="preserve" extradata="MT" uid="P:System.Web.Management.BufferedWebEventProvider.BufferMode">
          <source>The following code example shows how to use the <ph id="ph1">&lt;xref:System.Web.Management.BufferedWebEventProvider.BufferMode%2A&gt;</ph> property.</source>
          <target state="translated">В следующем примере кода показано, как использовать свойство <ph id="ph1">&lt;xref:System.Web.Management.BufferedWebEventProvider.BufferMode%2A&gt;</ph>.</target>       </trans-unit>
        <trans-unit id="120" translate="yes" xml:space="preserve" uid="M:System.Web.Management.BufferedWebEventProvider.Flush">
          <source>Moves the events from the provider's buffer into the event log.</source>
          <target state="translated">Перемещает события из буфера поставщика в журнал событий.</target>       </trans-unit>
        <trans-unit id="121" translate="yes" xml:space="preserve" extradata="MT" uid="M:System.Web.Management.BufferedWebEventProvider.Flush">
          <source>When this method is called, all the events in the buffer are immediately moved from the buffer to the log, regardless of how much time has elapsed since last write or how many events are in the buffer.</source>
          <target state="translated">При вызове этого метода все события в буфере немедленно перемещаются из буфера в журнал, независимо от того, сколько времени прошло с момента последней записи или количества событий в буфере.</target>       </trans-unit>
        <trans-unit id="122" translate="yes" xml:space="preserve" extradata="MT" uid="M:System.Web.Management.BufferedWebEventProvider.Flush">
          <source>The time of the last write is reset to the time of the flushing action.</source>
          <target state="translated">Время последней записи сбрасывается до времени выполнения очистки.</target>       </trans-unit>
        <trans-unit id="123" translate="yes" xml:space="preserve" extradata="MT" uid="M:System.Web.Management.BufferedWebEventProvider.Flush">
          <source>The following code example shows how to use the <ph id="ph1">&lt;xref:System.Web.Management.BufferedWebEventProvider.Flush%2A&gt;</ph> method.</source>
          <target state="translated">В следующем примере кода показано применение метода <ph id="ph1">&lt;xref:System.Web.Management.BufferedWebEventProvider.Flush%2A&gt;</ph>.</target>       </trans-unit>
        <trans-unit id="124" translate="yes" xml:space="preserve" uid="M:System.Web.Management.BufferedWebEventProvider.Initialize(System.String,System.Collections.Specialized.NameValueCollection)">
          <source>The name used in the configuration file to identify this provider.</source>
          <target state="translated">Имя, используемое в файле конфигурации для определения этого поставщика.</target>       </trans-unit>
        <trans-unit id="125" translate="yes" xml:space="preserve" uid="M:System.Web.Management.BufferedWebEventProvider.Initialize(System.String,System.Collections.Specialized.NameValueCollection)">
          <source>A <ph id="ph1">&lt;see cref="T:System.Collections.Specialized.NameValueCollection" /&gt;</ph> that specifies the attributes assigned for this provider in the configuration file.</source>
          <target state="translated"><ph id="ph1">&lt;see cref="T:System.Collections.Specialized.NameValueCollection" /&gt;</ph>, указывающий атрибуты, назначенные этому поставщику в файле конфигурации.</target>       </trans-unit>
        <trans-unit id="126" translate="yes" xml:space="preserve" uid="M:System.Web.Management.BufferedWebEventProvider.Initialize(System.String,System.Collections.Specialized.NameValueCollection)">
          <source>Sets the initial values for this object.</source>
          <target state="translated">Задает первоначальные значения для этого объекта.</target>       </trans-unit>
        <trans-unit id="127" translate="yes" xml:space="preserve" extradata="MT" uid="M:System.Web.Management.BufferedWebEventProvider.Initialize(System.String,System.Collections.Specialized.NameValueCollection)">
          <source>ASP.NET calls the <ph id="ph1">&lt;xref:System.Web.Management.BufferedWebEventProvider.Initialize%2A&gt;</ph> method after calling the <ph id="ph2">&lt;xref:System.Web.Management.BufferedWebEventProvider.%23ctor%2A&gt;</ph> constructor.</source>
          <target state="translated">ASP.NET вызывает <ph id="ph1">&lt;xref:System.Web.Management.BufferedWebEventProvider.Initialize%2A&gt;</ph> метод после вызова <ph id="ph2">&lt;xref:System.Web.Management.BufferedWebEventProvider.%23ctor%2A&gt;</ph> конструктор.</target>       </trans-unit>
        <trans-unit id="128" translate="yes" xml:space="preserve" extradata="MT" uid="M:System.Web.Management.BufferedWebEventProvider.Initialize(System.String,System.Collections.Specialized.NameValueCollection)">
          <source>This method is called to initialize the <ph id="ph1">&lt;xref:System.Web.Management.BufferedWebEventProvider&gt;</ph> with the configuration settings and name specified in the configuration file.</source>
          <target state="translated">Этот метод вызывается для инициализации <ph id="ph1">&lt;xref:System.Web.Management.BufferedWebEventProvider&gt;</ph> с именем, указанным в файле конфигурации и параметры конфигурации.</target>       </trans-unit>
        <trans-unit id="129" translate="yes" xml:space="preserve" extradata="MT" uid="M:System.Web.Management.BufferedWebEventProvider.Initialize(System.String,System.Collections.Specialized.NameValueCollection)">
          <source>The following code example shows how to use the <ph id="ph1">&lt;xref:System.Web.Management.BufferedWebEventProvider.Initialize%2A&gt;</ph> method.</source>
          <target state="translated">В следующем примере кода показано применение метода <ph id="ph1">&lt;xref:System.Web.Management.BufferedWebEventProvider.Initialize%2A&gt;</ph>.</target>       </trans-unit>
        <trans-unit id="130" translate="yes" xml:space="preserve" uid="M:System.Web.Management.BufferedWebEventProvider.ProcessEvent(System.Web.Management.WebBaseEvent)">
          <source>The <ph id="ph1">&lt;see cref="T:System.Web.Management.WebBaseEvent" /&gt;</ph> object to process.</source>
          <target state="translated">Объект <ph id="ph1">&lt;see cref="T:System.Web.Management.WebBaseEvent" /&gt;</ph>, который требуется обработать.</target>       </trans-unit>
        <trans-unit id="131" translate="yes" xml:space="preserve" uid="M:System.Web.Management.BufferedWebEventProvider.ProcessEvent(System.Web.Management.WebBaseEvent)">
          <source>Processes the event passed to the provider.</source>
          <target state="translated">Обрабатывает событие, переданное поставщику.</target>       </trans-unit>
        <trans-unit id="132" translate="yes" xml:space="preserve" extradata="MT" uid="M:System.Web.Management.BufferedWebEventProvider.ProcessEvent(System.Web.Management.WebBaseEvent)">
          <source>This is the method that ASP.NET health monitoring calls to start the processing of the event.</source>
          <target state="translated">Это метод, который вызывается мониторингом состояния ASP.NET для запуска обработки события.</target>       </trans-unit>
        <trans-unit id="133" translate="yes" xml:space="preserve" extradata="MT" uid="M:System.Web.Management.BufferedWebEventProvider.ProcessEvent(System.Web.Management.WebBaseEvent)">
          <source>If buffering is enabled, the event information is buffered; otherwise, it is dispatched to the current logging mechanism.</source>
          <target state="translated">Если буферизация включена, сведения о событии помещаются в буфер; в противном случае оно отправляется текущего механизма ведения журнала.</target>       </trans-unit>
        <trans-unit id="134" translate="yes" xml:space="preserve" extradata="MT" uid="M:System.Web.Management.BufferedWebEventProvider.ProcessEvent(System.Web.Management.WebBaseEvent)">
          <source>The following code example shows how to implement the <ph id="ph1">&lt;xref:System.Web.Management.BufferedWebEventProvider.ProcessEvent%2A&gt;</ph> method.</source>
          <target state="translated">В следующем примере кода демонстрируется реализация метода <ph id="ph1">&lt;xref:System.Web.Management.BufferedWebEventProvider.ProcessEvent%2A&gt;</ph>.</target>       </trans-unit>
        <trans-unit id="135" translate="yes" xml:space="preserve" uid="M:System.Web.Management.BufferedWebEventProvider.ProcessEventFlush(System.Web.Management.WebEventBufferFlushInfo)">
          <source>A <ph id="ph1">&lt;see cref="T:System.Web.Management.WebEventBufferFlushInfo" /&gt;</ph> that contains buffering information.</source>
          <target state="translated"><ph id="ph1">&lt;see cref="T:System.Web.Management.WebEventBufferFlushInfo" /&gt;</ph>, содержащий сведения о буферизации.</target>       </trans-unit>
        <trans-unit id="136" translate="yes" xml:space="preserve" uid="M:System.Web.Management.BufferedWebEventProvider.ProcessEventFlush(System.Web.Management.WebEventBufferFlushInfo)">
          <source>Processes the buffered events.</source>
          <target state="translated">Обрабатывает события в буфере.</target>       </trans-unit>
        <trans-unit id="137" translate="yes" xml:space="preserve" extradata="MT" uid="M:System.Web.Management.BufferedWebEventProvider.ProcessEventFlush(System.Web.Management.WebEventBufferFlushInfo)">
          <source>The <ph id="ph1">&lt;xref:System.Web.Management.BufferedWebEventProvider.ProcessEventFlush%2A&gt;</ph> method processes the messages that have been buffered.</source>
          <target state="translated"><ph id="ph1">&lt;xref:System.Web.Management.BufferedWebEventProvider.ProcessEventFlush%2A&gt;</ph> Метод обрабатывает сообщения, которые были буферизировать.</target>       </trans-unit>
        <trans-unit id="138" translate="yes" xml:space="preserve" extradata="MT" uid="M:System.Web.Management.BufferedWebEventProvider.ProcessEventFlush(System.Web.Management.WebEventBufferFlushInfo)">
          <source>ASP.NET health monitoring calls the method when the flushing of the buffer is required.</source>
          <target state="translated">Наблюдение за работоспособностью ASP.NET вызывает метод, когда требуется очистка буфера.</target>       </trans-unit>
        <trans-unit id="139" translate="yes" xml:space="preserve" extradata="MT" uid="M:System.Web.Management.BufferedWebEventProvider.ProcessEventFlush(System.Web.Management.WebEventBufferFlushInfo)">
          <source>The intervals at which flushing is required is determined by the parameter value of the <ph id="ph1">`bufferMode`</ph> attribute in the <ph id="ph2">`providers`</ph> element in the <ph id="ph3">`healthMonitoring`</ph> configuration section.</source>
          <target state="translated">Интервалы, в какие списания требуется определяется по значению параметра <ph id="ph1">`bufferMode`</ph> атрибута в <ph id="ph2">`providers`</ph> элемент в <ph id="ph3">`healthMonitoring`</ph> раздел конфигурации.</target>       </trans-unit>
        <trans-unit id="140" translate="yes" xml:space="preserve" extradata="MT" uid="M:System.Web.Management.BufferedWebEventProvider.ProcessEventFlush(System.Web.Management.WebEventBufferFlushInfo)">
          <source>The following code example shows how to implement the <ph id="ph1">&lt;xref:System.Web.Management.BufferedWebEventProvider.ProcessEventFlush%2A&gt;</ph> method.</source>
          <target state="translated">В следующем примере кода демонстрируется реализация метода <ph id="ph1">&lt;xref:System.Web.Management.BufferedWebEventProvider.ProcessEventFlush%2A&gt;</ph>.</target>       </trans-unit>
        <trans-unit id="141" translate="yes" xml:space="preserve" uid="M:System.Web.Management.BufferedWebEventProvider.Shutdown">
          <source>Performs tasks associated with shutting down the provider.</source>
          <target state="translated">Выполняет задачи, связанные с завершением работы поставщика.</target>       </trans-unit>
        <trans-unit id="142" translate="yes" xml:space="preserve" extradata="MT" uid="M:System.Web.Management.BufferedWebEventProvider.Shutdown">
          <source>ASP.NET calls the <ph id="ph1">&lt;xref:System.Web.Management.BufferedWebEventProvider.Shutdown%2A&gt;</ph> method when the application domain hosting the Web application terminates.</source>
          <target state="translated">ASP.NET вызывает <ph id="ph1">&lt;xref:System.Web.Management.BufferedWebEventProvider.Shutdown%2A&gt;</ph> метод при завершении домен приложения, содержащий веб-приложения.</target>       </trans-unit>
        <trans-unit id="143" translate="yes" xml:space="preserve" extradata="MT" uid="M:System.Web.Management.BufferedWebEventProvider.Shutdown">
          <source>The method is called to perform tasks that will allow the application to end gracefully, such as closing resources.</source>
          <target state="translated">Метод вызывается для выполнения задач, позволяющих приложению корректно завершить работу, например закрывающиеся ресурсы.</target>       </trans-unit>
        <trans-unit id="144" translate="yes" xml:space="preserve" uid="P:System.Web.Management.BufferedWebEventProvider.UseBuffering">
          <source>Gets a value indicating whether the provider is in buffered mode.</source>
          <target state="translated">Получает значение, указывающее, использует ли данный поставщик режим буферизации.</target>       </trans-unit>
        <trans-unit id="145" translate="yes" xml:space="preserve" extradata="MT" uid="P:System.Web.Management.BufferedWebEventProvider.UseBuffering">
          <source><ph id="ph1">&lt;see langword="true" /&gt;</ph> if the provider is in buffered mode; otherwise, <ph id="ph2">&lt;see langword="false" /&gt;</ph>.</source>
          <target state="translated"><ph id="ph1">&lt;see langword="true" /&gt;</ph>, если поставщик находится в режиме буферизации, в противном случае <ph id="ph2">&lt;see langword="false" /&gt;</ph>.</target>       </trans-unit>
        <trans-unit id="146" translate="yes" xml:space="preserve" extradata="MT" uid="P:System.Web.Management.BufferedWebEventProvider.UseBuffering">
          <source>The default is <ph id="ph1">&lt;see langword="true" /&gt;</ph>.</source>
          <target state="translated">Значение по умолчанию: <ph id="ph1">&lt;see langword="true" /&gt;</ph>.</target>       </trans-unit>
        <trans-unit id="147" translate="yes" xml:space="preserve" extradata="MT" uid="P:System.Web.Management.BufferedWebEventProvider.UseBuffering">
          <source>The <ph id="ph1">&lt;xref:System.Web.Management.BufferedWebEventProvider.UseBuffering%2A&gt;</ph> property contains the value defined by the <ph id="ph2">`buffer`</ph> attribute in the <ph id="ph3">`providers`</ph> element of the <ph id="ph4">`healthMonitoring`</ph> section.</source>
          <target state="translated"><ph id="ph1">&lt;xref:System.Web.Management.BufferedWebEventProvider.UseBuffering%2A&gt;</ph> Свойство содержит значение, определяемое <ph id="ph2">`buffer`</ph> атрибута в <ph id="ph3">`providers`</ph> элемент <ph id="ph4">`healthMonitoring`</ph> раздела.</target>       </trans-unit>
        <trans-unit id="148" translate="yes" xml:space="preserve" extradata="MT" uid="P:System.Web.Management.BufferedWebEventProvider.UseBuffering">
          <source>The following code example shows how to use the <ph id="ph1">&lt;xref:System.Web.Management.BufferedWebEventProvider.UseBuffering%2A&gt;</ph> property.</source>
          <target state="translated">В следующем примере кода показано, как использовать свойство <ph id="ph1">&lt;xref:System.Web.Management.BufferedWebEventProvider.UseBuffering%2A&gt;</ph>.</target>       </trans-unit>
      </group>
    </body>
  </file>
</xliff>